{"name":"Connector Data","nodeType":"project","project":"Connector Data","datasetType":"project","layer":"Connector Data","in":[{"name":"credreg_alfacre_connector_data","project":"Connector Data","out":[],"in":[],"datasetType":"Table","layer":"Raw"},{"name":"cr_source2_connector_data","project":"Connector Data","out":[],"in":[],"datasetType":"Table","layer":"Raw"}],"out":[{"name":"cr_connector_data_41","project":"Connector Data","out":[],"in":[],"datasetType":"Table","layer":"DataMart"},{"name":"cr_connector_data_54","project":"Connector Data","out":[],"in":[],"datasetType":"Table","layer":"DataMart"},{"name":"cr_connector_data_0","project":"Connector Data","out":[],"in":[],"datasetType":"Table","layer":"DataMart"},{"name":"cr_connector_data_3","project":"Connector Data","out":[],"in":[],"datasetType":"Table","layer":"DataMart"},{"name":"cr_connector_data_6","project":"Connector Data","out":[],"in":[],"datasetType":"Table","layer":"DataMart"},{"name":"cr_connector_data_22","project":"Connector Data","out":[],"in":[],"datasetType":"Table","layer":"DataMart"},{"name":"cr_connector_data_40","project":"Connector Data","out":[],"in":[],"datasetType":"Table","layer":"DataMart"},{"name":"cr_connector_data_48","project":"Connector Data","out":[],"in":[],"datasetType":"Table","layer":"DataMart"},{"name":"cr_connector_data_52","project":"Connector Data","out":[],"in":[],"datasetType":"Table","layer":"DataMart"}],"fields":[]}